[
    {
      "name": "破刀",
      "品级": "低级灵器",
      "攻击加成": 10,
      "防御加成": 10,
      "生命加成": 10,
      "暴击加成":0.01,
      "爆伤加成": 0.01,
      "闪避加成": 0.01,
      "等级":1,
      "exp":0
    },
    {
      "name": "破碎之盾",
      "品级": "低级灵器",
      "攻击加成": 5,
      "防御加成": 20,
      "生命加成": 15,
      "暴击加成":0.01,
      "爆伤加成": 0.01,
      "闪避加成": 0.03,
      "等级":1,
      "exp":0
    },
    {
      "name": "破伤风之剑",
      "品级": "低级灵器",
      "攻击加成": 10,
      "防御加成": 25,
      "生命加成": 15,
      "暴击加成":0.01,
      "爆伤加成": 0.03,
      "闪避加成": 0.03,
      "等级":1,
      "exp":0
    },
    {
      "name": "炽热战斧",
      "品级": "高级灵器",
      "攻击加成": 40,
      "防御加成": 25,
      "生命加成": 30,
      "暴击加成":0.05,
      "爆伤加成": 0.06,
      "闪避加成": 0.04,
      "等级":1,
      "exp":0
    },
    {
      "name": "寒冰法杖",
      "品级": "中级灵器",
      "攻击加成": 30,
      "防御加成": 10,
      "生命加成": 25,
      "暴击加成":0.02,
      "爆伤加成": 0.03,
      "闪避加成": 0.02,
      "等级":1,
      "exp":0
    },
    {
      "name": "雷霆之锤",
      "品级": "高级灵器",
      "攻击加成": 45,
      "防御加成": 20,
      "暴击加成":0.05,
      "爆伤加成": 0.06,
      "生命加成": 35,
      "闪避加成": 0.03,
      "等级":1,
      "exp":0
    },
    {
      "name": "幽影匕首",
      "品级": "中级灵器",
      "攻击加成": 35,
      "防御加成": 15,
      "暴击加成":0.02,
      "爆伤加成": 0.03,
      "生命加成": 20,
      "闪避加成": 0.05,
      "等级":1,
      "exp":0
    },
    {
      "name": "风暴长弓",
      "品级": "高级灵器",
      "攻击加成": 50,
      "防御加成": 10,
      "暴击加成":0.05,
      "爆伤加成": 0.06,
      "生命加成": 25,
      "闪避加成": 0.02,
      "等级":1,
      "exp":0
    },
    {
      "name": "翡翠项链",
      "品级": "低级灵器",
      "攻击加成": 5,
      "防御加成": 5,
      "暴击加成":0.01,
      "爆伤加成": 0.01,
      "生命加成": 30,
      "闪避加成": 0.01,
      "等级":1,
      "exp":0
    },
    {
      "name": "炎龙戒指",
      "品级": "中级灵器",
      "攻击加成": 20,
      "防御加成": 10,
      "暴击加成":0.05,
      "爆伤加成": 0.06,
      "生命加成": 20,
      "闪避加成": 0.03,
      "等级":1,
      "exp":0
    },
    {
      "name": "黎明之弓",
      "品级": "中级灵器",
      "攻击加成": 25,
      "防御加成": 20,
      "暴击加成":0.05,
      "爆伤加成": 0.07,
      "生命加成": 25,
      "闪避加成": 0.04,
      "等级":1,
      "exp":0
    },
    {
      "name": "月光披风",
      "品级": "高级灵器",
      "攻击加成": 15,
      "防御加成": 30,
      "暴击加成":0.05,
      "爆伤加成": 0.06,
      "生命加成": 40,
      "闪避加成": 0.04,
      "等级":1,
      "exp":0
    },
    {
      "name": "星辰头盔",
      "品级": "中级灵器",
      "攻击加成": 10,
      "防御加成": 25,
      "暴击加成":0.02,
      "爆伤加成": 0.03,
      "生命加成": 30,
      "闪避加成": 0.02,
      "等级":1,
      "exp":0
    },
    {
      "name": "狂战胸甲",
      "品级": "高级灵器",
      "攻击加成": 25,
      "防御加成": 40,
      "暴击加成":0.05,
      "爆伤加成": 0.06,
      "生命加成": 50,
      "闪避加成": 0.01,
      "等级":1,
      "exp":0
    },
    {
      "name": "灵动战靴",
      "品级": "中级灵器",
      "攻击加成": 15,
      "防御加成": 20,
      "暴击加成":0.02,
      "爆伤加成": 0.03,
      "生命加成": 25,
      "闪避加成": 0.06,
      "等级":1,
      "exp":0
    },
    {
        "name": "炽天使之剑",
        "品级": "高级灵器",
        "攻击加成": 60,
        "防御加成": 20,
        "生命加成": 30,
        "暴击加成":0.05,
        "爆伤加成": 0.06,
        "闪避加成": 0.03,
        "等级":1,
        "exp":0
    },
    {
        "name": "暗影魔杖",
        "品级": "高级灵器",
        "攻击加成": 55,
        "防御加成": 15,
        "暴击加成":0.05,
        "爆伤加成": 0.06,
        "生命加成": 35,
        "闪避加成": 0.04,
        "等级":1,
        "exp":0
    },
    {
        "name": "寒冰法杖",
        "品级": "中级灵器",
        "攻击加成": 40,
        "防御加成": 10,
        "暴击加成":0.02,
        "爆伤加成": 0.03,
        "生命加成": 25,
        "闪避加成": 0.02,
        "等级":1,
        "exp":0
    },
    {
        "name": "炎魔之弓",
        "品级": "高级灵器",
        "攻击加成": 65,
        "防御加成": 15,
        "暴击加成":0.05,
        "爆伤加成": 0.06,
        "生命加成": 20,
        "闪避加成": 0.03,
        "等级":1,
        "exp":0
    },
    {
        "name": "狼牙棒",
        "品级": "低级灵器",
        "攻击加成": 15,
        "防御加成": 5,
        "暴击加成":0.01,
        "爆伤加成": 0.01,
        "生命加成": 10,
        "闪避加成": 0.01,
        "等级":1,
        "exp":0
    },
    {
        "name": "碧水剑",
        "品级": "中级灵器",
        "攻击加成": 35,
        "防御加成": 10,
        "暴击加成":0.02,
        "爆伤加成": 0.03,
        "生命加成": 15,
        "闪避加成": 0.02,
        "等级":1,
        "exp":0
    },
    {
        "name": "破空斧",
        "品级": "高级灵器",
        "攻击加成": 50,
        "防御加成": 25,
        "暴击加成":0.05,
        "爆伤加成": 0.06,
        "生命加成": 30,
        "闪避加成": 0.03,
        "等级":1,
        "exp":0
    },
    {
        "name": "噬魂刃",
        "品级": "中级灵器",
        "攻击加成": 45,
        "防御加成": 15,
        "暴击加成":0.02,
        "爆伤加成": 0.03,
        "生命加成": 20,
        "闪避加成": 0.04,
        "等级":1,
        "exp":0
    },
    {
        "name": "天雷锤",
        "品级": "低级灵器",
        "攻击加成": 20,
        "防御加成": 10,
        "暴击加成":0.01,
        "爆伤加成": 0.01,
        "生命加成": 15,
        "闪避加成": 0.01,
        "等级":1,
        "exp":0
    },
    {
        "name": "绿波扇",
        "品级": "中级灵器",
        "攻击加成": 30,
        "防御加成": 20,
        "暴击加成":0.02,
        "爆伤加成": 0.03,
        "生命加成": 25,
        "闪避加成": 0.03,
        "等级":1,
        "exp":0
    },
    {
        "name": "破碎之刃",
        "品级": "高级灵器",
        "攻击加成": 55,
        "防御加成": 20,
        "暴击加成":0.05,
        "爆伤加成": 0.06,
        "生命加成": 35,
        "闪避加成": 0.05,
        "等级":1,
        "exp":0
    },
    {
        "name": "翡翠戒指",
        "品级": "低级灵器",
        "攻击加成": 5,
        "防御加成": 5,
        "暴击加成":0.01,
        "爆伤加成": 0.01,
        "生命加成": 20,
        "闪避加成": 0.01,
        "等级":1,
        "exp":0
    },
    {
        "name": "龙鳞护腕",
        "品级": "中级灵器",
        "攻击加成": 15,
        "防御加成": 25,
        "暴击加成":0.02,
        "爆伤加成": 0.03,
        "生命加成": 30,
        "闪避加成": 0.02,
        "等级":1,
        "exp":0
    },
    {
        "name": "炽炎披风",
        "品级": "高级灵器",
        "攻击加成": 20,
        "防御加成": 35,
        "暴击加成":0.05,
        "爆伤加成": 0.06,
        "生命加成": 40,
        "闪避加成": 0.04,
        "等级":1,
        "exp":0
    },
    {
        "name": "幽冥头盔",
        "品级": "中级灵器",
        "攻击加成": 10,
        "防御加成": 20,
        "暴击加成":0.02,
        "爆伤加成": 0.03,
        "生命加成": 25,
        "闪避加成": 0.03,
        "等级":1,
        "exp":0
    },
    {
        "name": "狮心胸甲",
        "品级": "高级灵器",
        "攻击加成": 25,
        "防御加成": 45,
        "生命加成": 50,
        "暴击加成":0.02,
        "爆伤加成": 0.03,
        "闪避加成": 0.02,
        "等级":1,
        "exp":0
    },
    {
        "name": "风行战靴",
        "品级": "中级灵器",
        "攻击加成": 15,
        "防御加成": 15,
        "暴击加成":0.02,
        "爆伤加成": 0.03,
        "生命加成": 20,
        "闪避加成": 0.05,
        "等级":1,
        "exp":0
    },
    {
        "name": "炼狱项链",
        "品级": "高级灵器",
        "攻击加成": 30,
        "防御加成": 10,
        "暴击加成":0.05,
        "爆伤加成": 0.06,
        "生命加成": 40,
        "闪避加成": 0.03,
        "等级":1,
        "exp":0
    },
    {
        "name": "光辉耳环",
        "品级": "中级灵器",
        "攻击加成": 20,
        "防御加成": 10,
        "暴击加成":0.02,
        "爆伤加成": 0.03,
        "生命加成": 30,
        "闪避加成": 0.02,
        "等级":1,
        "exp":0
    },
    {
        "name": "暗夜指环",
        "品级": "低级灵器",
        "攻击加成": 10,
        "防御加成": 5,
        "暴击加成":0.01,
        "爆伤加成": 0.01,
        "生命加成": 15,
        "闪避加成": 0.01,
        "等级":1,
        "exp":0
    },
    {
        "name": "破晓之弓",
        "品级": "高级灵器",
        "攻击加成": 70,
        "防御加成": 10,
        "暴击加成":0.05,
        "爆伤加成": 0.06,
        "生命加成": 20,
        "闪避加成": 0.03,
        "等级":1,
        "exp":0
    },
    {
        "name": "狂风法杖",
        "品级": "中级灵器",
        "攻击加成": 45,
        "防御加成": 15,
        "生命加成": 25,
        "暴击加成":0.02,
        "爆伤加成": 0.03,
        "闪避加成": 0.04,
        "等级":1,
        "exp":0
    },
    {
        "name": "炼金术士之杖",
        "品级": "低级灵器",
        "攻击加成": 20,
        "防御加成": 5,
        "生命加成": 10,
        "暴击加成":0.01,
        "爆伤加成": 0.01,
        "闪避加成": 0.01,
        "等级":1,
        "exp":0
    },
    {
        "name": "破军长枪",
        "品级": "高级灵器",
        "攻击加成": 60,
        "防御加成": 25,
        "生命加成": 35,
        "暴击加成":0.05,
        "爆伤加成": 0.06,
        "闪避加成": 0.02,
        "等级":1,
        "exp":0
    },
    {
        "name": "碎骨锤",
        "品级": "中级灵器",
        "攻击加成": 40,
        "防御加成": 20,
        "生命加成": 30,
        "暴击加成":0.02,
        "爆伤加成": 0.03,
        "闪避加成": 0.03,
        "等级":1,
        "exp":0
    },
    {
        "name": "破魔刀",
        "品级": "低级灵器",
        "攻击加成": 25,
        "防御加成": 10,
        "暴击加成":0.01,
        "爆伤加成": 0.01,
        "生命加成": 15,
        "闪避加成": 0.01,
        "等级":1,
        "exp":0
    },
    {
        "name": "无尽之刃",
        "品级": "高级灵器",
        "攻击加成": 75,
        "防御加成": 30,
        "暴击加成":0.05,
        "爆伤加成": 0.06,
        "生命加成": 40,
        "闪避加成": 0.05,
        "等级":1,
        "exp":0
    },
    {
        "name": "狂暴之戟",
        "品级": "中级灵器",
        "攻击加成": 50,
        "防御加成": 25,
        "暴击加成":0.02,
        "爆伤加成": 0.03,
        "生命加成": 35,
        "闪避加成": 0.03,
        "等级":1,
        "exp":0
    },
    {
        "name": "破灭之杖",
        "品级": "低级灵器",
        "攻击加成": 30,
        "防御加成": 10,
        "生命加成": 20,
        "暴击加成":0.01,
        "爆伤加成": 0.01,
        "闪避加成": 0.01,
        "等级":1,
        "exp":0
    },
    {
        "name": "神秘权杖",
        "品级": "高级灵器",
        "攻击加成": 65,
        "防御加成": 20,
        "生命加成": 45,
        "暴击加成":0.03,
        "爆伤加成": 0.05,
        "闪避加成": 0.04,
        "等级":1,
        "exp":0
    },
    {
        "name": "干将莫邪",
        "品级": "高级灵器",
        "攻击加成": 65,
        "防御加成": 20,
        "生命加成": 45,
        "暴击加成":0.03,
        "爆伤加成": 0.05,
        "闪避加成": 0.04,
        "等级":1,
        "exp":0
    },
    {
        "name": "梦幻浩然长弓",
        "品级": "帝兵",
        "攻击加成": 650,
        "防御加成": 600,
        "暴击加成":0.1,
        "爆伤加成": 0.13,
        "生命加成": 500,
        "闪避加成": 0.04,
        "等级":1,
        "exp":0
    },
    {
        "name": "诗仙",
        "品级": "帝兵",
        "攻击加成": 800,
        "防御加成": 500,
        "暴击加成":0.1,
        "爆伤加成": 0.2,
        "生命加成": 600,
        "闪避加成": 0.06,
        "等级":1,
        "exp":0
    },
    {
        "name": "史记",
        "品级": "帝兵",
        "攻击加成": 700,
        "防御加成": 550,
        "暴击加成":0.1,
        "爆伤加成": 0.11,
        "生命加成": 650,
        "闪避加成": 0.06,
        "等级":1,
        "exp":0
    },
    {
        "name": "盘龙玉笛",
        "品级": "帝兵",
        "攻击加成": 750,
        "防御加成": 550,
        "暴击加成":0.1,
        "爆伤加成": 0.15,
        "生命加成": 700,
        "闪避加成": 0.07,
        "等级":1,
        "exp":0
    }
]

  